expkg/__init__.py
expkg/examp.py
expkg-1.0.0.dist-info/METADATA
expkg-1.0.0.dist-info/WHEEL
expkg-1.0.0.dist-info/licenses/LICENSE.txt
expkg-1.0.0.dist-info/RECORD
